[{"id":"1478204856161275924","channel_id":"1478161522453778585","author":{"id":"248222192297443328","username":"dogs80","avatar":"eafc37fc641eb97a7f1aad55dbb17e32","discriminator":"0","public_flags":64,"flags":64,"banner":null,"accent_color":null,"global_name":"dogs80","avatar_decoration_data":null,"collectibles":null,"display_name_styles":null,"banner_color":null,"clan":null,"primary_guild":null},"content":"This is good idea, unfortunately I ran into the same thing during my test, I would reschedule if system was having issues.","timestamp":"2026-03-03T01:38:21.427000+00:00","edited_timestamp":null,"tts":false,"mention_everyone":false,"mentions":[],"attachments":[],"embeds":[],"reactions":[{"emoji":{"id":null,"name":"👍🏻"},"count":1,"count_details":{"burst":0,"normal":1},"burst_colors":[],"me_burst":false,"burst_me":false,"me":false,"burst_count":0}],"pinned":false,"type":0,"flags":0,"components":[],"position":0,"userName":"dogs80"},{"id":"1478161522453778585","channel_id":"1478161522453778585","author":{"id":"392674501395087360","username":"throwitbackonahoethrowitbackhoee","avatar":"a_9de686c397cc3891f8b717159c687583","discriminator":"0","public_flags":64,"flags":64,"banner":null,"accent_color":null,"global_name":"kablow","avatar_decoration_data":{"asset":"a_b524fa5c3f80fbea3865a5d130ab5aef","sku_id":"1352407446282440704","expires_at":null},"collectibles":{"nameplate":{"sku_id":"1377377712104018071","asset":"nameplates/nameplates_v2/starfall_tides/","label":"COLLECTIBLES_NAMEPLATES_V2_STARFALL_TIDES_A11Y","palette":"teal"}},"display_name_styles":{"font_id":10,"effect_id":3,"colors":[13018645]},"banner_color":null,"clan":{"identity_guild_id":"1465584280808722455","identity_enabled":true,"tag":"MMM","badge":"226250a3dcd3c30f66f7649b4521f14e"},"primary_guild":{"identity_guild_id":"1465584280808722455","identity_enabled":true,"tag":"MMM","badge":"226250a3dcd3c30f66f7649b4521f14e"}},"content":"I am just now finding out that Evadus was down it would have helped if it said that prior to starting my test i thought my honorlock was detecting the RDP but it may have just been Evadus down i’ll have to test for my next one and hopefully it works. Great tool I really hope it works for Honorlock.","timestamp":"2026-03-02T22:46:09.866000+00:00","edited_timestamp":null,"tts":false,"mention_everyone":false,"mentions":[],"attachments":[],"embeds":[],"reactions":[{"emoji":{"id":null,"name":"👍"},"count":2,"count_details":{"burst":0,"normal":2},"burst_colors":[],"me_burst":false,"burst_me":false,"me":false,"burst_count":0}],"pinned":false,"type":0,"flags":0,"components":[],"position":0,"userName":"throwitbackonahoethrowitbackhoee"}]